{
"type": "FeatureCollection",
"name": "LOCALISATION_KRAKATOA_WGS84",
"crs": { "type": "name", "properties": { "name": "urn:ogc:def:crs:OGC:1.3:CRS84" } },
"xy_coordinate_resolution": 1e-15,
"features": [
{ "type": "Feature", "properties": { "id": 1, "nom": "Krakatoa" }, "geometry": { "type": "Point", "coordinates": [ 105.422178737223263, -6.102960344453129 ] } }
]
}
